ner_metrics/__init__.py
ner_metrics/ner_metrics.py
ner_metrics-0.1.2.dist-info/LICENSE
ner_metrics-0.1.2.dist-info/METADATA
ner_metrics-0.1.2.dist-info/WHEEL
ner_metrics-0.1.2.dist-info/top_level.txt
ner_metrics-0.1.2.dist-info/RECORD
